pydomus/__init__.py
pydomus/__main__.py
pydomus/api/__init__.py
pydomus/cli/__init__.py
pydomus-0.13.data/scripts/pydomus
pydomus-0.13.dist-info/METADATA
pydomus-0.13.dist-info/WHEEL
pydomus-0.13.dist-info/top_level.txt
pydomus-0.13.dist-info/RECORD
